main.py
envfetch-1.1.1.dist-info/LICENSE
envfetch-1.1.1.dist-info/METADATA
envfetch-1.1.1.dist-info/WHEEL
envfetch-1.1.1.dist-info/top_level.txt
envfetch-1.1.1.dist-info/RECORD
